cozi/__init__.py
cozi/exceptions.py
py_cozi-1.0.4.dist-info/LICENSE
py_cozi-1.0.4.dist-info/METADATA
py_cozi-1.0.4.dist-info/WHEEL
py_cozi-1.0.4.dist-info/top_level.txt
py_cozi-1.0.4.dist-info/RECORD
