Metadata-Version: 2.1
Name: py-cozi
Version: 1.0.4
Summary: Cozi Unofficial Python Package
Home-page: https://github.com/Wetzel402/py-cozi
Author: Cody Wetzel
Author-email: wetzelredistribution@gmail.com
License: MIT
Keywords: unoffical Cozi api
Classifier: Programming Language :: Python :: 3
Classifier: License :: OSI Approved :: MIT License
Classifier: Operating System :: OS Independent
Requires-Python: >=3.5
License-File: LICENSE
Requires-Dist: aiohttp >=3.9.2
Requires-Dist: beautifulsoup4 >=4.10.0
